{
    "server": {
        "address": "10.0.0.1/24",
        "server_end_point": "94.103.81.237:51830",
        "server_publickey": "EJK3m6r0A1cdMk692EziYIgbzkRouM6XRvAL4k01VQo=",
        "server_privatekey": "OGo3LpK+GFHl1rgCWm9vZCoW2nU0GyZR9NmbDQr/xlk="
    },
    "clients": {
        "Криптограф": {
            "chat_id": 608862111,
            "address": "10.0.0.23/32",
            "publickey": "Ac74K609d9Rh1G4HgJ6HPIz88AaNdH9XSslsFkyNEWE=",
            "privatekey": "WMjzqSHCsAAVyrOWUZmPgIues5FTggTl5sCZzFtoBFc=",
            "created_at": "2023-07-13 14:11:32.184426",
            "expiration_of_sub_date": "2023-08-12 14:11:32.184426",
            "enable": true
        },
        "Ярослав": {
            "chat_id": 5824481563,
            "address": "10.0.0.22/32",
            "publickey": "lzDC9OfyCYq4zSukieqF1ZUX1O8/7DokGFAyidX3pG4=",
            "privatekey": "0Gt0nqeR7iwWWecgk6Dt8Sj7iMSjkKyQ86FPck1Phnk=",
            "created_at": "2023-07-13 12:00:12.527960",
            "expiration_of_sub_date": "2023-07-12 12:00:12.527960",
            "enable": false
        }
    }
}